Metadata-Version: 2.1
Name: notas-musicais-lj
Version: 0.1.2
Summary: Notas musicais é um CLI para ajudar na formação de escalas, acordes e campos harmônicos
License: MIT
Author: Leonardo Jacomussi
Author-email: leonardojacomussi@gmail.com
Requires-Python: >=3.9,<4.0
Classifier: Development Status :: 5 - Production/Stable
Classifier: Environment :: Console
Classifier: License :: OSI Approved :: MIT License
Classifier: Natural Language :: Portuguese (Brazilian)
Classifier: Programming Language :: Python :: 3
Classifier: Programming Language :: Python :: 3.9
Classifier: Programming Language :: Python :: 3.10
Classifier: Programming Language :: Python :: 3.11
Classifier: Programming Language :: Python :: 3.12
Classifier: Topic :: Education
Requires-Dist: rich (>=13.8.0,<14.0.0)
Requires-Dist: typer (>=0.12.5,<0.13.0)
Project-URL: Bug Tracker, https://github.com/leonardojacomussi/notas-musicais/issues
Project-URL: Código, https://github.com/leonardojacomussi/notas-musicais
Project-URL: Documentação, https://notas-musicais-lj.readthedocs.io/en/latest/
